rjgtoys_cli-0.0.3-py3.8-nspkg.pth
rjgtoys/cli/__init__.py
rjgtoys/cli/_base.py
rjgtoys_cli-0.0.3.dist-info/LICENSE
rjgtoys_cli-0.0.3.dist-info/METADATA
rjgtoys_cli-0.0.3.dist-info/WHEEL
rjgtoys_cli-0.0.3.dist-info/namespace_packages.txt
rjgtoys_cli-0.0.3.dist-info/top_level.txt
rjgtoys_cli-0.0.3.dist-info/RECORD
