Metadata-Version: 2.1
Name: rjgtoys-cli
Version: 0.0.3
Summary: Command-line tool components
Home-page: https://github.com/bobgautier/rjgtoys-cli
Author: Robert J. Gautier
Author-email: bob.gautier@gmail.com
License: UNKNOWN
Platform: UNKNOWN
Classifier: Programming Language :: Python :: 3
Classifier: License :: OSI Approved :: MIT License
Classifier: Operating System :: OS Independent
Requires-Python: >=3.6
Requires-Dist: rjgtoys-xc
